vmw_cloudinit_metadata/__init__.py
vmw_cloudinit_metadata/cli/__init__.py
vmw_cloudinit_metadata/cli/app.py
vmw_cloudinit_metadata/cli/main.py
vmw_cloudinit_metadata/cli/commands/__init__.py
vmw_cloudinit_metadata/cli/commands/run.py
vmw_cloudinit_metadata/drivers/__init__.py
vmw_cloudinit_metadata/drivers/driver.py
vmw_cloudinit_metadata/drivers/file.py
vmw_cloudinit_metadata/vspc/__init__.py
vmw_cloudinit_metadata/vspc/async_telnet.py
vmw_cloudinit_metadata/vspc/server.py
vmw_cloudinit_metadata/vspc/vm_client.py
vmw_cloudinit_metadata-0.0.8.dist-info/METADATA
vmw_cloudinit_metadata-0.0.8.dist-info/RECORD
vmw_cloudinit_metadata-0.0.8.dist-info/WHEEL
vmw_cloudinit_metadata-0.0.8.dist-info/entry_points.txt
vmw_cloudinit_metadata-0.0.8.dist-info/pbr.json
vmw_cloudinit_metadata-0.0.8.dist-info/top_level.txt
