Metadata-Version: 2.1
Name: vmw-cloudinit-metadata
Version: 0.0.8
Summary: Library and Tool to run a Cloud-Init NoCloud compatible metadata server for VMWare VCenter
Home-page: https://github.com/rmb938/vmw-cloudinit-metadata/
Author: Ryan Belgrave
Author-email: rmb1993@gmail.com
License: MIT
Platform: UNKNOWN
Classifier: Development Status :: 3 - Alpha
Classifier: Environment :: Console
Classifier: Intended Audience :: Developers
Classifier: License :: OSI Approved :: MIT License
Classifier: Operating System :: OS Independent
Classifier: Programming Language :: Python
Classifier: Topic :: System :: Systems Administration
Requires-Dist: PyYAML (==3.12)
Requires-Dist: clify (==0.0.3)
Requires-Dist: pbr (==4.0.3)
Requires-Dist: schematics (==2.0.1)
Requires-Dist: cryptography (==2.1.4)
